moz_merino_ext.libs/libgcc_s-98a1ef30.so.1
moz_merino_ext/__init__.py
moz_merino_ext/__init__.pyi
moz_merino_ext/amp/__init__.py
moz_merino_ext/amp/__init__.pyi
moz_merino_ext/amp/py.typed
moz_merino_ext/moz_merino_ext.cpython-313t-x86_64-linux-musl.so
moz_merino_ext/py.typed
mozilla_merino_ext-0.2.0.dist-info/METADATA
mozilla_merino_ext-0.2.0.dist-info/WHEEL
mozilla_merino_ext-0.2.0.dist-info/licenses/LICENSE
mozilla_merino_ext-0.2.0.dist-info/RECORD
