Metadata-Version: 2.4
Name: mozilla-merino-ext
Version: 0.2.0
Requires-Dist: maturin>=1.8.7
License-File: LICENSE
License: MPL-2.0
Requires-Python: ~=3.13.0
